setup.py
distributions/Binomialdistribution.py
distributions/Gaussiandistribution.py
distributions/Generaldistribution.py
distributions/__init__.py
fananda_distributions.egg-info/PKG-INFO
fananda_distributions.egg-info/SOURCES.txt
fananda_distributions.egg-info/dependency_links.txt
fananda_distributions.egg-info/not-zip-safe
fananda_distributions.egg-info/top_level.txt